{
  "characters": [
    {
      "id": 1,
      "name": "Luke Skywalker",
      "pic": "https://vignette.wikia.nocookie.net/starwars/images/2/20/LukeTLJ.jpg",
      "homeworld": "tatooine"
    },
    {
      "id": 2,
      "name": "C-3PO",
      "pic": "https://vignette.wikia.nocookie.net/starwars/images/3/3f/C-3PO_TLJ_Card_Trader_Award_Card.png",
      "homeworld": "tatooine"
    },
    {
      "id": 3,
      "name": "R2-D2",
      "pic": "https://vignette.wikia.nocookie.net/starwars/images/e/eb/ArtooTFA2-Fathead.png",
      "homeworld": "naboo"
    },
    {
      "id": 4,
      "name": "Darth Vader",
      "pic": "https://vignette.wikia.nocookie.net/fr.starwars/images/3/32/Dark_Vador.jpg",
      "homeworld": "tatooine"
    },
    {
      "id": 5,
      "name": "Leia Organa",
      "pic": "https://vignette.wikia.nocookie.net/starwars/images/f/fc/Leia_Organa_TLJ.png",
      "homeworld": "alderaan"
    },
    {
      "id": 6,
      "name": "Owen Lars",
      "pic": "https://vignette.wikia.nocookie.net/starwars/images/e/eb/OwenCardTrader.png",
      "homeworld": "tatooine"
    },
    {
      "id": 7,
      "name": "Beru Whitesun lars",
      "pic": "https://vignette.wikia.nocookie.net/starwars/images/c/cc/BeruCardTrader.png",
      "homeworld": "tatooine"
    },
    {
      "id": 8,
      "name": "R5-D4",
      "pic": "https://vignette.wikia.nocookie.net/starwars/images/c/cb/R5-D4_Sideshow.png",
      "homeworld": "tatooine"
    },
    {
      "id": 9,
      "name": "Biggs Darklighter",
      "pic": "https://vignette.wikia.nocookie.net/starwars/images/0/00/BiggsHS-ANH.png",
      "homeworld": "tatooine"
    },
    {
      "id": 10,
      "name": "Obi-Wan Kenobi",
      "pic": "https://vignette.wikia.nocookie.net/starwars/images/4/4e/ObiWanHS-SWE.jpg",
      "homeworld": "stewjon"
    },
    {
      "id": 11,
      "name": "Anakin Skywalker",
      "pic": "https://vignette.wikia.nocookie.net/starwars/images/6/6f/Anakin_Skywalker_RotS.png",
      "homeworld": "tatooine"
    },
    {
      "id": 12,
      "name": "Wilhuff Tarkin",
      "pic": "https://vignette.wikia.nocookie.net/starwars/images/c/c1/Tarkininfobox.jpg",
      "homeworld": "eriadu"
    },
    {
      "id": 13,
      "name": "Chewbacca",
      "pic": "https://vignette.wikia.nocookie.net/starwars/images/4/48/Chewbacca_TLJ.png",
      "homeworld": "kashyyyk"
    },
    {
      "id": 14,
      "name": "Han Solo",
      "pic": "https://vignette.wikia.nocookie.net/starwars/images/e/e2/TFAHanSolo.png",
      "homeworld": "corellia"
    },
    {
      "id": 15,
      "name": "Greedo",
      "pic": "https://vignette.wikia.nocookie.net/starwars/images/c/c6/Greedo.jpg",
      "homeworld": "Rodia"
    },
    {
      "id": 16,
      "name": "Jabba Desilijic Tiure",
      "pic": "https://vignette.wikia.nocookie.net/starwars/images/7/7f/Jabba_SWSB.png",
      "homeworld": "tatooine"
    },
    {
      "id": 18,
      "name": "Wedge Antilles",
      "pic": "https://vignette.wikia.nocookie.net/starwars/images/6/60/WedgeHelmetless-ROTJHD.jpg",
      "homeworld": "corellia"
    },
    {
      "id": 19,
      "name": "Jek Tono Porkins",
      "pic": "https://vignette.wikia.nocookie.net/starwars/images/e/eb/JekPorkins-DB.png",
      "homeworld": "bestine"
    },
    {
      "id": 20,
      "name": "Yoda",
      "pic": "https://vignette.wikia.nocookie.net/starwars/images/d/d6/Yoda_SWSB.png"
    },
    {
      "id": 21,
      "name": "Palpatine",
      "pic": "https://vignette.wikia.nocookie.net/starwars/images/d/d8/Emperor_Sidious.png",
      "homeworld": "naboo"
    },
    {
      "id": 22,
      "name": "Boba Fett",
      "pic": "https://vignette.wikia.nocookie.net/starwars/images/7/79/Boba_Fett_HS_Fathead.png",
      "homeworld": "kamino"
    },
    {
      "id": 23,
      "name": "IG-88",
      "pic": "https://vignette.wikia.nocookie.net/starwars/images/f/f2/IG-88.png"
    },
    {
      "id": 24,
      "name": "Bossk",
      "pic": "https://vignette.wikia.nocookie.net/starwars/images/1/1d/Bossk.png",
      "homeworld": "trandosha"
    },
    {
      "id": 25,
      "name": "Lando Calrissian",
      "pic": "https://vignette.wikia.nocookie.net/starwars/images/8/8f/Lando_ROTJ.png",
      "homeworld": "socorro"
    },
    {
      "id": 26,
      "name": "Lobot",
      "pic": "https://vignette.wikia.nocookie.net/starwars/images/9/96/SWE_Lobot.jpg",
      "homeworld": "bespin"
    },
    {
      "id": 27,
      "name": "Ackbar",
      "pic": "https://vignette.wikia.nocookie.net/starwars/images/2/29/Admiral_Ackbar_RH.png",
      "homeworld": "mon cala"
    },
    {
      "id": 28,
      "name": "Mon Mothma",
      "pic": "https://vignette.wikia.nocookie.net/starwars/images/b/b7/MP-MonMothma.png",
      "homeworld": "chandrila"
    },
    {
      "id": 29,
      "name": "Arvel Crynyd",
      "pic": "https://vignette.wikia.nocookie.net/starwars/images/d/de/Arvel-crynyd.jpg"
    },
    {
      "id": 30,
      "name": "Wicket Systri Warrick",
      "pic": "https://vignette.wikia.nocookie.net/starwars/images/4/4f/Wicket_RotJ.png",
      "homeworld": "endor"
    },
    {
      "id": 31,
      "name": "Nien Nunb",
      "pic": "https://vignette.wikia.nocookie.net/starwars/images/1/14/Old_nien_nunb_-_profile.png",
      "homeworld": "sullust"
    },
    {
      "id": 32,
      "name": "Qui-Gon Jinn",
      "pic": "https://vignette.wikia.nocookie.net/starwars/images/f/f6/Qui-Gon_Jinn_Headshot_TPM.jpg",
      "homeworld": "coruscant"
    },
    {
      "id": 33,
      "name": "Nute Gunray",
      "pic": "https://vignette.wikia.nocookie.net/starwars/images/f/fd/Nute_Gunray_SWE.png",
      "homeworld": "neimoidia"
    },
    {
      "id": 34,
      "name": "Finis Valorum",
      "pic": "https://vignette.wikia.nocookie.net/starwars/images/5/51/ValorumPortrait-SWE.png",
      "homeworld": "coruscant"
    },
    {
      "id": 36,
      "name": "Jar Jar Binks",
      "pic": "https://vignette.wikia.nocookie.net/starwars/images/d/d2/Jar_Jar_aotc.jpg",
      "homeworld": "naboo"
    },
    {
      "id": 37,
      "name": "Roos Tarpals",
      "pic": "https://vignette.wikia.nocookie.net/starwars/images/c/ca/TarpalsHS.jpg",
      "homeworld": "naboo"
    },
    {
      "id": 38,
      "name": "Rugor Nass",
      "pic": "https://vignette.wikia.nocookie.net/starwars/images/d/d8/Bossnass.jpg",
      "homeworld": "naboo"
    },
    {
      "id": 39,
      "name": "Ric Olié",
      "pic": "https://vignette.wikia.nocookie.net/starwars/images/4/4c/RicOlieHS-SWE.png",
      "homeworld": "naboo"
    },
    {
      "id": 40,
      "name": "Watto",
      "pic": "https://vignette.wikia.nocookie.net/starwars/images/e/eb/WattoHS.jpg",
      "homeworld": "toydaria"
    },
    {
      "id": 41,
      "name": "Sebulba",
      "pic": "https://vignette.wikia.nocookie.net/starwars/images/1/14/Sebulba_Headshot_Closeup.png",
      "homeworld": "malastare"
    },
    {
      "id": 42,
      "name": "Quarsh Panaka",
      "pic": "https://vignette.wikia.nocookie.net/starwars/images/7/72/PanakaHS-TPM.png",
      "homeworld": "naboo"
    },
    {
      "id": 43,
      "name": "Shmi Skywalker",
      "pic": "https://vignette.wikia.nocookie.net/starwars/images/a/ad/ShmiSkywalkerDatabank_%28Repurposed%29.jpeg",
      "homeworld": "tatooine"
    },
    {
      "id": 44,
      "name": "Darth Maul",
      "pic": "https://vignette.wikia.nocookie.net/starwars/images/5/50/Darth_Maul_profile.png",
      "homeworld": "dathomir"
    },
    {
      "id": 45,
      "name": "Bib Fortuna",
      "pic": "https://vignette.wikia.nocookie.net/starwars/images/3/33/BibFortunaHS-ROTJ.png",
      "homeworld": "ryloth"
    },
    {
      "id": 46,
      "name": "Ayla Secura",
      "pic": "https://vignette.wikia.nocookie.net/starwars/images/f/f9/Aayla.jpg",
      "homeworld": "ryloth"
    },
    {
      "id": 48,
      "name": "Dud Bolt",
      "pic": "https://vignette.wikia.nocookie.net/starwars/images/7/73/Dud_Bolt_Podracer_Cockpit.png",
      "homeworld": "vulpter"
    },
    {
      "id": 49,
      "name": "Gasgano",
      "pic": "https://vignette.wikia.nocookie.net/starwars/images/5/57/GasganoHS-SWE.jpg",
      "homeworld": "troiken"
    },
    {
      "id": 50,
      "name": "Ben Quadinaros",
      "pic": "https://vignette.wikia.nocookie.net/starwars/images/7/7f/Cropped_Quadinaros.png",
      "homeworld": "tund"
    },
    {
      "id": 51,
      "name": "Mace Windu",
      "pic": "https://vignette.wikia.nocookie.net/starwars/images/5/58/Mace_ROTS.png",
      "homeworld": "haruun kal"
    },
    {
      "id": 52,
      "name": "Ki-Adi-Mundi",
      "pic": "https://vignette.wikia.nocookie.net/starwars/images/9/9e/KiAdiMundi.jpg",
      "homeworld": "cerea"
    },
    {
      "id": 53,
      "name": "Kit Fisto",
      "pic": "https://vignette.wikia.nocookie.net/starwars/images/4/4c/Kit_Fisto_Card_Trader.png",
      "homeworld": "glee anselm"
    },
    {
      "id": 54,
      "name": "Eeth Koth",
      "pic": "https://vignette.wikia.nocookie.net/starwars/images/4/4e/EethKothCardTrader.png",
      "homeworld": "nar shaddaa"
    },
    {
      "id": 55,
      "name": "Adi Gallia",
      "pic": "https://vignette.wikia.nocookie.net/starwars/images/b/ba/AdiGallia.jpg",
      "homeworld": "coruscant"
    },
    {
      "id": 56,
      "name": "Saesee Tiin",
      "pic": "https://vignette.wikia.nocookie.net/starwars/images/6/68/Saesee_Tiin_Card_Trader.jpg",
      "homeworld": "iktotch"
    },
    {
      "id": 57,
      "name": "Yarael Poof",
      "pic": "https://vignette.wikia.nocookie.net/starwars/images/6/66/Yarael_Poof_Canon.jpeg",
      "homeworld": "quermia"
    },
    {
      "id": 58,
      "name": "Plo Koon",
      "pic": "https://vignette.wikia.nocookie.net/starwars/images/b/bf/PloKoonCardTrader.png",
      "homeworld": "dorin"
    },
    {
      "id": 59,
      "name": "Mas Amedda",
      "pic": "https://vignette.wikia.nocookie.net/starwars/images/3/37/Mas_Amedda_SWCT.png",
      "homeworld": "champala"
    },
    {
      "id": 60,
      "name": "Gregar Typho",
      "pic": "https://vignette.wikia.nocookie.net/starwars/images/5/52/Gregar_Typho.jpg",
      "homeworld": "naboo"
    },
    {
      "id": 61,
      "name": "Cordé",
      "pic": "https://vignette.wikia.nocookie.net/starwars/images/b/b6/Cord%C3%A9_-_SW_Card_Trader.png",
      "homeworld": "naboo"
    },
    {
      "id": 62,
      "name": "Cliegg Lars",
      "pic": "https://vignette.wikia.nocookie.net/starwars/images/3/36/ClieggLarsHS-SWE.jpg",
      "homeworld": "tatooine"
    },
    {
      "id": 63,
      "name": "Poggle the Lesser",
      "pic": "https://vignette.wikia.nocookie.net/starwars/images/9/93/Poggle_the_lesser_-_sw_card_trader.png",
      "homeworld": "geonosis"
    },
    {
      "id": 64,
      "name": "Luminara Unduli",
      "pic": "https://vignette.wikia.nocookie.net/starwars/images/2/21/LuminaraHS-SWE_%28new%29.png",
      "homeworld": "mirial"
    },
    {
      "id": 65,
      "name": "Barriss Offee",
      "pic": "https://vignette.wikia.nocookie.net/starwars/images/3/37/Barrisprofile2.jpg",
      "homeworld": "mirial"
    },
    {
      "id": 66,
      "name": "Dormé",
      "pic": "https://vignette.wikia.nocookie.net/starwars/images/1/18/Dormesenate.jpg",
      "homeworld": "naboo"
    },
    {
      "id": 67,
      "name": "Dooku",
      "pic": "https://vignette.wikia.nocookie.net/starwars/images/b/b8/Dooku_Headshot.jpg",
      "homeworld": "serenno"
    },
    {
      "id": 68,
      "name": "Bail Prestor Organa",
      "pic": "https://vignette.wikia.nocookie.net/starwars/images/5/50/Bail_Organa_Mug.jpg",
      "homeworld": "alderaan"
    },
    {
      "id": 69,
      "name": "Jango Fett",
      "pic": "https://vignette.wikia.nocookie.net/starwars/images/5/56/JangoInfobox.png",
      "homeworld": "concord dawn"
    },
    {
      "id": 70,
      "name": "Zam Wesell",
      "pic": "https://vignette.wikia.nocookie.net/starwars/images/7/7d/Clawdite.jpg",
      "homeworld": "zolan"
    },
    {
      "id": 71,
      "name": "Dexter Jettster",
      "pic": "https://vignette.wikia.nocookie.net/starwars/images/6/6c/DexterHS-SWE.jpg",
      "homeworld": "ojom"
    },
    {
      "id": 72,
      "name": "Lama Su",
      "pic": "https://vignette.wikia.nocookie.net/starwars/images/7/73/Lama_Su.jpg",
      "homeworld": "kamino"
    },
    {
      "id": 73,
      "name": "Taun We",
      "pic": "https://vignette.wikia.nocookie.net/starwars/images/9/9c/TaunWe.jpg",
      "homeworld": "kamino"
    },
    {
      "id": 74,
      "name": "Jocasta Nu",
      "pic": "https://vignette.wikia.nocookie.net/starwars/images/1/15/Jocasta_Nu_SWE.png",
      "homeworld": "coruscant"
    },
    {
      "id": 47,
      "name": "Ratts Tyerell",
      "pic": "https://vignette.wikia.nocookie.net/starwars/images/6/68/RattsHS.jpg",
      "homeworld": "aleen"
    },
    {
      "id": 75,
      "name": "R4-P17",
      "pic": "https://vignette.wikia.nocookie.net/starwars/images/6/6b/R4-P17.jpg"
    },
    {
      "id": 76,
      "name": "Wat Tambor",
      "pic": "https://vignette.wikia.nocookie.net/starwars/images/a/a5/Wat_Tambor.png",
      "homeworld": "skako"
    },
    {
      "id": 77,
      "name": "San Hill",
      "pic": "https://vignette.wikia.nocookie.net/starwars/images/6/6f/SanHill_hs.jpg",
      "homeworld": "scipio"
    },
    {
      "id": 78,
      "name": "Shaak Ti",
      "pic": "https://vignette.wikia.nocookie.net/starwars/images/2/20/Shaak_Ti_closeup-SWE.png",
      "homeworld": "shili"
    },
    {
      "id": 79,
      "name": "Grievous",
      "pic": "https://vignette.wikia.nocookie.net/starwars/images/d/de/Grievoushead.jpg",
      "homeworld": "kalee"
    },
    {
      "id": 80,
      "name": "Tarfful",
      "pic": "https://vignette.wikia.nocookie.net/starwars/images/3/37/Tarfful_RotS.png",
      "homeworld": "kashyyyk"
    },
    {
      "id": 81,
      "name": "Raymus Antilles",
      "pic": "https://vignette.wikia.nocookie.net/starwars/images/8/80/Raymus_card_trader.png",
      "homeworld": "alderaan"
    },
    {
      "id": 82,
      "name": "Sly Moore",
      "pic": "https://vignette.wikia.nocookie.net/starwars/images/e/ec/SlyMooreIsWatchingYouPoop-OfficialPix.jpg",
      "homeworld": "umbara"
    },
    {
      "id": 83,
      "name": "Tion Medon",
      "pic": "https://vignette.wikia.nocookie.net/starwars/images/4/43/Tion_Medon.jpg",
      "homeworld": "utapau"
    },
    {
      "id": 84,
      "name": "Finn",
      "pic": "https://vignette.wikia.nocookie.net/starwars/images/a/af/Finn_TLJ_Collector%27s_Edition.png"
    },
    {
      "id": 85,
      "name": "Rey",
      "pic": "https://vignette.wikia.nocookie.net/starwars/images/f/f8/ReyTLJEntertainmentWeeklyNovember.png",
      "homeworld": "jakku"
    },
    {
      "id": 86,
      "name": "Poe Dameron",
      "pic": "https://vignette.wikia.nocookie.net/starwars/images/7/79/Poe_Dameron_TLJ.png",
      "homeworld": "yavin 4"
    },
    {
      "id": 87,
      "name": "BB8",
      "pic": "https://vignette.wikia.nocookie.net/starwars/images/6/68/BB8-Fathead.png"
    },
    {
      "id": 88,
      "name": "Captain Phasma",
      "pic": "https://vignette.wikia.nocookie.net/starwars/images/0/02/Phasma.png",
      "homeworld": "parnassos"
    },
    {
      "id": 35,
      "name": "Padmé Amidala",
      "pic": "https://vignette.wikia.nocookie.net/starwars/images/b/b2/Padmegreenscrshot.jpg",
      "homeworld": "naboo"
    }
  ]
}
